CHANGES.txt
LICENSE.txt
MANIFEST
README.rst
setup.py
django_epfl/__init__.py
django_epfl/context_processors.py
django_epfl/middleware.py
django_epfl.egg-info/PKG-INFO
django_epfl.egg-info/SOURCES.txt
django_epfl.egg-info/dependency_links.txt
django_epfl.egg-info/not-zip-safe
django_epfl.egg-info/top_level.txt
django_epfl/static/admin/css/changelists.css
django_epfl/static/admin/css/epfl-admin.css
django_epfl/static/admin/css/forms.css
django_epfl/static/admin/css/widgets.css
django_epfl/static/admin/img/admin/arrow-down.gif
django_epfl/static/admin/img/admin/arrow-up.gif
django_epfl/static/admin/img/admin/changelist-bg.gif
django_epfl/static/admin/img/admin/changelist-bg_rtl.gif
django_epfl/static/admin/img/admin/chooser-bg.gif
django_epfl/static/admin/img/admin/chooser_stacked-bg.gif
django_epfl/static/admin/img/admin/default-bg-reverse.gif
django_epfl/static/admin/img/admin/default-bg.gif
django_epfl/static/admin/img/admin/deleted-overlay.gif
django_epfl/static/admin/img/admin/icon-no.gif
django_epfl/static/admin/img/admin/icon-unknown.gif
django_epfl/static/admin/img/admin/icon-yes.gif
django_epfl/static/admin/img/admin/icon_addlink.gif
django_epfl/static/admin/img/admin/icon_alert.gif
django_epfl/static/admin/img/admin/icon_calendar.gif
django_epfl/static/admin/img/admin/icon_changelink.gif
django_epfl/static/admin/img/admin/icon_clock.gif
django_epfl/static/admin/img/admin/icon_deletelink.gif
django_epfl/static/admin/img/admin/icon_error.gif
django_epfl/static/admin/img/admin/icon_searchbox.png
django_epfl/static/admin/img/admin/icon_success.gif
django_epfl/static/admin/img/admin/inline-delete-8bit.png
django_epfl/static/admin/img/admin/inline-delete.png
django_epfl/static/admin/img/admin/inline-restore-8bit.png
django_epfl/static/admin/img/admin/inline-restore.png
django_epfl/static/admin/img/admin/inline-splitter-bg.gif
django_epfl/static/admin/img/admin/nav-bg-grabber.gif
django_epfl/static/admin/img/admin/nav-bg-reverse.gif
django_epfl/static/admin/img/admin/nav-bg.gif
django_epfl/static/admin/img/admin/selector-add.gif
django_epfl/static/admin/img/admin/selector-addall.gif
