Metadata-Version: 1.1
Name: django-epfl
Version: 1.5.6
Summary: Django utils for EPFL sites
Home-page: http://kis-doc.epfl.ch/django
Author: Romain Gehrig
Author-email: romain.gehrig@epfl.ch
License: GNU LGPLv3
Keywords: epfl,templates,django_epfl,tequila,django-tequila,django-pagination,django
Platform: UNKNOWN
Classifier: Programming Language :: Python
Classifier: Topic :: Software Development :: Libraries :: Python Modules
Classifier: Framework :: Django
Classifier: Environment :: Web Environment
Requires: setuptools
